{
    "haskell.nix": {
        "branch": "hkm/emcc",
        "description": "Alternative Haskell Infrastructure for Nixpkgs",
        "homepage": "https://input-output-hk.github.io/haskell.nix",
        "owner": "input-output-hk",
        "repo": "haskell.nix",
        "rev": "0464f55cf703bf6a717e8db44c9524e49ce715e5",
        "sha256": "1mwj5h4hpsaz17jskkn8kfwbdrgfcqf999x449lnpyhhmkmwd9yy",
        "type": "tarball",
        "url": "https://github.com/input-output-hk/haskell.nix/archive/0464f55cf703bf6a717e8db44c9524e49ce715e5.tar.gz",
        "url_template": "https://github.com/<owner>/<repo>/archive/<rev>.tar.gz"
    },
    "iohk-nix": {
        "branch": "master",
        "description": "nix scripts shared across projects",
        "homepage": null,
        "owner": "input-output-hk",
        "repo": "iohk-nix",
        "rev": "4efc38924c64c23a582c84950c8c25f72ff049cc",
        "sha256": "0nhwyrd0xc72yj5q3jqa2wl4khp4g7n72i45cxy2rgn9nrp8wqh0",
        "type": "tarball",
        "url": "https://github.com/input-output-hk/iohk-nix/archive/4efc38924c64c23a582c84950c8c25f72ff049cc.tar.gz",
        "url_template": "https://github.com/<owner>/<repo>/archive/<rev>.tar.gz"
    }
}
